{
  "id": "beerentorte",
  "title": "Beerentorte",
  "category": "Torten",
  "yield": {
    "amount": 1,
    "unit": "torte (ø  cm)"
  },
  "ingredients": [
    {
      "group": "Für den Boden",
      "amount": 100,
      "unit": "g",
      "name": "Datteln"
    },
    {
      "group": "Für den Boden",
      "amount": 200,
      "unit": "g",
      "name": "Mandeln (am besten schon gemahlen)"
    },
    {
      "group": "Für den Boden",
      "amount": 20,
      "unit": "g",
      "name": "feste Margarine"
    },
    {
      "group": "Für den Boden",
      "amount": 2.5,
      "unit": "g",
      "name": "Salz",
      "note": "entspricht 0.5 TL"
    },
    {
      "group": "Für die Füllung",
      "amount": 50,
      "unit": "g",
      "name": "Agavendicksaft"
    },
    {
      "group": "Für die Füllung",
      "amount": 6,
      "unit": "g",
      "name": "Vanillearoma",
      "note": "entspricht 2 TL"
    },
    {
      "group": "Für die Füllung",
      "amount": 800,
      "unit": "g",
      "name": "pflanzlicher Quark"
    },
    {
      "group": "Für die Füllung",
      "amount": 1,
      "unit": "Stück",
      "name": "Limette"
    },
    {
      "group": "Für die Füllung",
      "amount": 375,
      "unit": "g",
      "name": "Brombeeren (oder Heidelbeeren)"
    },
    {
      "group": "Für die Füllung",
      "amount": 4,
      "unit": "Blatt",
      "name": "Agar Agar (z.B. von RUF)"
    },
    {
      "group": "Für die Dekoration",
      "amount": 125,
      "unit": "g",
      "name": "frische Brombeeren"
    },
    {
      "group": "Für die Dekoration",
      "amount": 50,
      "unit": "g",
      "name": "gehackte Mandeln"
    },
    {
      "group": "Für die Dekoration",
      "amount": 1,
      "unit": "Stück",
      "name": "Limette"
    }
  ],
  "steps": [
    "Boden Datteln in heißem Wasser einweichen.",
    "Datteln, Mandeln, Margarine und Salz in einen Zerkleinerer geben und etwa 1 Minute auf hoher Stufe vermengen.",
    "Die Mischung in eine Kuchenform (18 cm Durchmesser) geben oder in einen Tortenring, der schon auf einer Servierplatte/Tortenplatte platziert wurde.",
    "Den Boden mit den Finger oder einem Esslöffel festdrücken, sodass ein grader Boden entsteht.",
    "Im Kühlschrank kaltstellen.",
    "Füllung Den Agavendicksaft, das Vanillearoma, den Saft einer Limette und den pflanzlichen Quark mit einem Schneebesen in einer Schüssel glatt rühren.",
    "2/3 der Beeren waschen und in einem hohen Gefäß pürieren.",
    "Das pürierten Brombeeren in einen großen Topf oder eine tiefe Pfanne geben und mit 300 g der Quarkmasse auffüllen.",
    "Auf mittlerer Hitze und unter ständigem Rühren zum Köcheln bringen.",
    "4 Blatt Agar Agar hinzugeben und mindestens 2 Minuten köcheln lassen.",
    "Dabei ständig rühren, bis sich die Blätter komplett auflösen.",
    "Das Fruchtmousse vom Herd nehmen und den restlichen Quark mit einem Schneebesen einrühren.",
    "Beiseitestellen.",
    "1/3 der Beeren waschen und gleichmäßig auf dem Kuchenboden platzieren.",
    "Die Brombeer-Quark-Füllung nun vorsichtig auf den Boden gießen und am Ende glatt streichen.",
    "Den Kuchen am besten über Nacht (mindestens 4 Stunden) im Kühlschrank aufbewahren.",
    "Die Torte aus dem Kühlschrank nehmen und mit Brombeeren, Limettenscheiben und gehackten Mandeln dekorieren."
  ],
  "source": {
    "url": "https://www.zuckerjagdwurst.com/de/rezepte/vegane-brombeertorte-ohne-backen"
  },
  "images": [
    "beerentorte.webp"
  ],
  "dateAdded": "2026-07-17"
}
